MANIFEST.in
setup.py
xpin/__init__.py
xpin/constants.py
xpin/log.py
xpin.egg-info/PKG-INFO
xpin.egg-info/SOURCES.txt
xpin.egg-info/dependency_links.txt
xpin.egg-info/not-zip-safe
xpin.egg-info/requires.txt
xpin.egg-info/top_level.txt
xpin/api/__init__.py
xpin/api/api.py
xpin/app/__init__.py
xpin/app/app.py
xpin/app/extensions.py
xpin/app/models.py
xpin/app/backends/__init__.py
xpin/app/backends/ding.py
xpin/app/backends/mail.py
xpin/app/backends/sendcloud.py
xpin/app/templates/index.html
xpin/app/templates/admin/login.html
xpin/app/templates/admin/master.html
xpin/app/views/__init__.py
xpin/app/views/frontend.py
xpin/app/views/admin/__init__.py
xpin/app/views/admin/admin.py
xpin/app/views/admin/forms.py
xpin/bin/xpin