Metadata-Version: 1.0
Name: xpin
Version: 0.1.69
Summary: pin create/verify
Home-page: https://github.com/dantezhu/xpin
Author: dantezhu
Author-email: zny2008@gmail.com
License: BSD
Platform: any
